[
 {
  "id": "AED-01",
  "name": "AED (OSM)",
  "addr": "lokalizacja wg OSM",
  "lat": 50.08326,
  "lon": 18.98755,
  "indoor": false,
  "access": "godziny",
  "hours": "b.d.",
  "signage": false,
  "inspection": "brak",
  "owner": "wg OSM",
  "source": "OSM",
  "osm_id": 13628880001,
  "loc_desc": "",
  "check_date": "2026-03-06",
  "phone": ""
 },
 {
  "id": "AED-02",
  "name": "AED (OSM)",
  "addr": "lokalizacja wg OSM",
  "lat": 50.08722,
  "lon": 18.99518,
  "indoor": true,
  "access": "godziny",
  "hours": "b.d.",
  "signage": false,
  "inspection": "brak",
  "owner": "wg OSM",
  "source": "OSM",
  "osm_id": 13628887301,
  "loc_desc": "",
  "check_date": "2025-12-07",
  "phone": ""
 },
 {
  "id": "AED-03",
  "name": "Media Markt Polska Sp. z o.o.",
  "addr": "Punkt Informacyjny, przy głównym wejściu",
  "lat": 50.0972,
  "lon": 19.00678,
  "indoor": true,
  "access": "godziny",
  "hours": "Mo-Su 10:00-21:00",
  "signage": false,
  "inspection": "brak",
  "owner": "Media Markt Polska Sp. z o.o.",
  "source": "OSM",
  "osm_id": 12142923101,
  "loc_desc": "Punkt Informacyjny, przy głównym wejściu",
  "check_date": "2024-08-28",
  "phone": "+48 799 353 535"
 },
 {
  "id": "AED-04",
  "name": "AED (OSM)",
  "addr": "lokalizacja wg OSM",
  "lat": 50.09729,
  "lon": 19.03384,
  "indoor": true,
  "access": "godziny",
  "hours": "b.d.",
  "signage": false,
  "inspection": "brak",
  "owner": "wg OSM",
  "source": "OSM",
  "osm_id": 9559169217,
  "loc_desc": "",
  "check_date": "",
  "phone": ""
 },
 {
  "id": "AED-05",
  "name": "Castorama Polska Sp. z o.o.",
  "addr": "Parter, obok Punktu Zwrotów",
  "lat": 50.09889,
  "lon": 19.00883,
  "indoor": true,
  "access": "godziny",
  "hours": "Mo-Su 07:00-21:00",
  "signage": false,
  "inspection": "brak",
  "owner": "Castorama Polska Sp. z o.o.",
  "source": "OSM",
  "osm_id": 12142918001,
  "loc_desc": "Parter, obok Punktu Zwrotów",
  "check_date": "2024-08-28",
  "phone": "+48 32 395 71 00"
 },
 {
  "id": "AED-06",
  "name": "Przedsiębiorstwo Komunikacji Miejskiej w Tychach",
  "addr": "Na dyspozytorni PKM Tychy",
  "lat": 50.1005,
  "lon": 19.01738,
  "indoor": true,
  "access": "24/7",
  "hours": "całodobowo",
  "signage": false,
  "inspection": "brak",
  "owner": "Przedsiębiorstwo Komunikacji Miejskiej w Tychach",
  "source": "OSM",
  "osm_id": 11771427700,
  "loc_desc": "Na dyspozytorni PKM Tychy",
  "check_date": "2024-08-28",
  "phone": "+48 32 217 10 41"
 },
 {
  "id": "AED-07",
  "name": "Wodny Park Tychy",
  "addr": "Na ścianie w korytarzu przejścia ze strefy rekreacyjnej do strefy sportowej",
  "lat": 50.10337,
  "lon": 18.97788,
  "indoor": true,
  "access": "godziny",
  "hours": "Mo-Su 10:00-22:00",
  "signage": false,
  "inspection": "brak",
  "owner": "Wodny Park Tychy",
  "source": "OSM",
  "osm_id": 12142936601,
  "loc_desc": "Na ścianie w korytarzu przejścia ze strefy rekreacyjnej do strefy sportowej",
  "check_date": "2024-08-28",
  "phone": "+48 32 438 88 35"
 },
 {
  "id": "AED-08",
  "name": "Filar na pasażu przy punkcie informacyjnym - nap",
  "addr": "Filar na pasażu przy punkcie informacyjnym - naprzeciwko apteki",
  "lat": 50.10468,
  "lon": 18.98945,
  "indoor": true,
  "access": "godziny",
  "hours": "b.d.",
  "signage": false,
  "inspection": "brak",
  "owner": "wg OSM",
  "source": "OSM",
  "osm_id": 13732055603,
  "loc_desc": "Filar na pasażu przy punkcie informacyjnym - naprzeciwko apteki",
  "check_date": "2026-04-15",
  "phone": ""
 },
 {
  "id": "AED-09",
  "name": "Miejska Biblioteka Publiczna w Tychach",
  "addr": "Na ścianie przy głównym wejściu do budynku, obok stanowiska ochrony",
  "lat": 50.1067,
  "lon": 18.98523,
  "indoor": true,
  "access": "godziny",
  "hours": "Mo-Su 08:00-20:00",
  "signage": false,
  "inspection": "brak",
  "owner": "Miejska Biblioteka Publiczna w Tychach",
  "source": "OSM",
  "osm_id": 9522340189,
  "loc_desc": "Na ścianie przy głównym wejściu do budynku, obok stanowiska ochrony",
  "check_date": "2024-08-28",
  "phone": "+48 32 416 90 94"
 },
 {
  "id": "AED-10",
  "name": "hs medical",
  "addr": "ul. Przejazdowa 8",
  "lat": 50.10822,
  "lon": 19.04181,
  "indoor": false,
  "access": "24/7",
  "hours": "całodobowo",
  "signage": false,
  "inspection": "brak",
  "owner": "hs medical",
  "source": "OSM",
  "osm_id": 13857654301,
  "loc_desc": "ul. Przejazdowa 8",
  "check_date": "",
  "phone": ""
 },
 {
  "id": "AED-11",
  "name": "w kapsule przy wejściu do szkoły od strony ul. S",
  "addr": "w kapsule przy wejściu do szkoły od strony ul. Skalnej",
  "lat": 50.11276,
  "lon": 18.96447,
  "indoor": false,
  "access": "24/7",
  "hours": "całodobowo",
  "signage": false,
  "inspection": "brak",
  "owner": "wg OSM",
  "source": "OSM",
  "osm_id": 13433841541,
  "loc_desc": "w kapsule przy wejściu do szkoły od strony ul. Skalnej",
  "check_date": "",
  "phone": ""
 },
 {
  "id": "AED-12",
  "name": "ZS nr 4 Tychy",
  "addr": "ZS nr 4 Tychy",
  "lat": 50.1141,
  "lon": 18.97982,
  "indoor": false,
  "access": "godziny",
  "hours": "b.d.",
  "signage": false,
  "inspection": "brak",
  "owner": "wg OSM",
  "source": "OSM",
  "osm_id": 13439738802,
  "loc_desc": "ZS nr 4 Tychy",
  "check_date": "",
  "phone": ""
 },
 {
  "id": "AED-13",
  "name": "w budynku, na ścianie po prawej stronie od główn",
  "addr": "w budynku, na ścianie po prawej stronie od głównego wejścia",
  "lat": 50.11456,
  "lon": 18.99679,
  "indoor": true,
  "access": "godziny",
  "hours": "Mo-We 07:30-15:30; Th 07:30-17:30; Fr 07:30-13:30; Sa-Su, PH off",
  "signage": false,
  "inspection": "brak",
  "owner": "wg OSM",
  "source": "OSM",
  "osm_id": 13639361158,
  "loc_desc": "w budynku, na ścianie po prawej stronie od głównego wejścia",
  "check_date": "",
  "phone": ""
 },
 {
  "id": "AED-14",
  "name": "Biuro obsługi klienta",
  "addr": "Biuro obsługi klienta",
  "lat": 50.11534,
  "lon": 18.98334,
  "indoor": true,
  "access": "godziny",
  "hours": "Mo-Fr 07:00-16:00",
  "signage": false,
  "inspection": "brak",
  "owner": "wg OSM",
  "source": "OSM",
  "osm_id": 12558370333,
  "loc_desc": "Biuro obsługi klienta",
  "check_date": "",
  "phone": ""
 },
 {
  "id": "AED-15",
  "name": "po lewej stronie wejścia do budynku",
  "addr": "po lewej stronie wejścia do budynku",
  "lat": 50.11586,
  "lon": 19.0032,
  "indoor": false,
  "access": "godziny",
  "hours": "b.d.",
  "signage": false,
  "inspection": "brak",
  "owner": "wg OSM",
  "source": "OSM",
  "osm_id": 13628860201,
  "loc_desc": "po lewej stronie wejścia do budynku",
  "check_date": "2026-03-08",
  "phone": "+48322180050"
 },
 {
  "id": "AED-16",
  "name": "z lewej strony wejścia do budynku",
  "addr": "z lewej strony wejścia do budynku",
  "lat": 50.11594,
  "lon": 19.00873,
  "indoor": false,
  "access": "godziny",
  "hours": "b.d.",
  "signage": false,
  "inspection": "brak",
  "owner": "wg OSM",
  "source": "OSM",
  "osm_id": 13628857801,
  "loc_desc": "z lewej strony wejścia do budynku",
  "check_date": "2026-03-08",
  "phone": ""
 },
 {
  "id": "AED-17",
  "name": "AED (OSM)",
  "addr": "lokalizacja wg OSM",
  "lat": 50.11755,
  "lon": 18.99782,
  "indoor": false,
  "access": "godziny",
  "hours": "b.d.",
  "signage": false,
  "inspection": "brak",
  "owner": "wg OSM",
  "source": "OSM",
  "osm_id": 13628864701,
  "loc_desc": "",
  "check_date": "2026-03-08",
  "phone": "+48322273633"
 },
 {
  "id": "AED-18",
  "name": "po prawej stronie wejścia do budynku",
  "addr": "po prawej stronie wejścia do budynku",
  "lat": 50.11933,
  "lon": 18.9991,
  "indoor": false,
  "access": "godziny",
  "hours": "b.d.",
  "signage": false,
  "inspection": "brak",
  "owner": "wg OSM",
  "source": "OSM",
  "osm_id": 13628862501,
  "loc_desc": "po prawej stronie wejścia do budynku",
  "check_date": "2026-03-08",
  "phone": "+48322273634"
 },
 {
  "id": "AED-19",
  "name": "z prawej strony wejścia do budynku",
  "addr": "z prawej strony wejścia do budynku",
  "lat": 50.11955,
  "lon": 18.99196,
  "indoor": false,
  "access": "godziny",
  "hours": "b.d.",
  "signage": false,
  "inspection": "brak",
  "owner": "wg OSM",
  "source": "OSM",
  "osm_id": 13628867502,
  "loc_desc": "z prawej strony wejścia do budynku",
  "check_date": "2026-03-08",
  "phone": "+48609818222"
 },
 {
  "id": "AED-20",
  "name": "z prawej strony wejścia do budynku",
  "addr": "z prawej strony wejścia do budynku",
  "lat": 50.12013,
  "lon": 18.99406,
  "indoor": false,
  "access": "godziny",
  "hours": "b.d.",
  "signage": false,
  "inspection": "brak",
  "owner": "wg OSM",
  "source": "OSM",
  "osm_id": 13628867501,
  "loc_desc": "z prawej strony wejścia do budynku",
  "check_date": "2026-03-08",
  "phone": "+48322275799"
 },
 {
  "id": "AED-21",
  "name": "przy kasie MOSiR",
  "addr": "przy kasie MOSiR",
  "lat": 50.12148,
  "lon": 18.99264,
  "indoor": true,
  "access": "godziny",
  "hours": "Mo-Su 06:00-22:00",
  "signage": false,
  "inspection": "brak",
  "owner": "wg OSM",
  "source": "OSM",
  "osm_id": 9522340188,
  "loc_desc": "przy kasie MOSiR",
  "check_date": "",
  "phone": ""
 },
 {
  "id": "AED-22",
  "name": "Komedna Miejska Policji w Tychach",
  "addr": "W recepcji po prawej stronie",
  "lat": 50.12284,
  "lon": 18.98585,
  "indoor": true,
  "access": "24/7",
  "hours": "całodobowo",
  "signage": false,
  "inspection": "brak",
  "owner": "Komedna Miejska Policji w Tychach",
  "source": "OSM",
  "osm_id": 9384168036,
  "loc_desc": "W recepcji po prawej stronie",
  "check_date": "2024-08-28",
  "phone": "+48 47 855 12 00"
 },
 {
  "id": "AED-23",
  "name": "na ścianie po prawej stronie od głównego wejścia",
  "addr": "na ścianie po prawej stronie od głównego wejścia do pasażu przy Biurze Paszportowym",
  "lat": 50.12405,
  "lon": 18.97844,
  "indoor": true,
  "access": "godziny",
  "hours": "Mo-Sa 05:00-22:30",
  "signage": false,
  "inspection": "brak",
  "owner": "wg OSM",
  "source": "OSM",
  "osm_id": 13628883001,
  "loc_desc": "na ścianie po prawej stronie od głównego wejścia do pasażu przy Biurze Paszportowym",
  "check_date": "2026-03-08",
  "phone": ""
 },
 {
  "id": "AED-24",
  "name": "Pasaż Kultury Andromeda",
  "addr": "Pasaż Kultury Andromeda",
  "lat": 50.12641,
  "lon": 18.98241,
  "indoor": true,
  "access": "godziny",
  "hours": "Mo-Su 08:00-16:00",
  "signage": false,
  "inspection": "brak",
  "owner": "Pasaż Kultury Andromeda",
  "source": "OSM",
  "osm_id": 9522340190,
  "loc_desc": "Pasaż Kultury Andromeda",
  "check_date": "",
  "phone": "+48 32 227 36 11"
 },
 {
  "id": "AED-25",
  "name": "w dyżurce po prawej stronie od wejścia do budynk",
  "addr": "w dyżurce po prawej stronie od wejścia do budynku",
  "lat": 50.12668,
  "lon": 18.97438,
  "indoor": true,
  "access": "24/7",
  "hours": "całodobowo",
  "signage": false,
  "inspection": "brak",
  "owner": "wg OSM",
  "source": "OSM",
  "osm_id": 13639361159,
  "loc_desc": "w dyżurce po prawej stronie od wejścia do budynku",
  "check_date": "",
  "phone": ""
 },
 {
  "id": "AED-26",
  "name": "Teatr Mały",
  "addr": "Teatr Mały",
  "lat": 50.12827,
  "lon": 18.98054,
  "indoor": true,
  "access": "godziny",
  "hours": "Mo-Su 08:00-16:00",
  "signage": false,
  "inspection": "brak",
  "owner": "Teatr Mały",
  "source": "OSM",
  "osm_id": 9522340191,
  "loc_desc": "Teatr Mały",
  "check_date": "",
  "phone": "+48 32 227 36 11"
 },
 {
  "id": "AED-27",
  "name": "RPWiK Tychy S.A. ul. Sadowa 4. umieszczony w bud",
  "addr": "RPWiK Tychy S.A. ul. Sadowa 4. umieszczony w budynku administracyjnym 2, parter po lewej stronie, obok drzwi wejściowych. Dostęp całodobowy.",
  "lat": 50.1296,
  "lon": 18.99123,
  "indoor": true,
  "access": "godziny",
  "hours": "b.d.",
  "signage": false,
  "inspection": "brak",
  "owner": "wg OSM",
  "source": "OSM",
  "osm_id": 12702662901,
  "loc_desc": "RPWiK Tychy S.A. ul. Sadowa 4. umieszczony w budynku administracyjnym 2, parter po lewej stronie, obok drzwi wejściowych. Dostęp całodobowy.",
  "check_date": "2025-03-27",
  "phone": ""
 },
 {
  "id": "AED-28",
  "name": "Tauron",
  "addr": "Hol główny przy portierni",
  "lat": 50.13559,
  "lon": 18.9655,
  "indoor": true,
  "access": "godziny",
  "hours": "b.d.",
  "signage": false,
  "inspection": "brak",
  "owner": "Tauron",
  "source": "OSM",
  "osm_id": 13722332039,
  "loc_desc": "Hol główny przy portierni",
  "check_date": "",
  "phone": ""
 },
 {
  "id": "AED-29",
  "name": "Na ścianie, naprzeciwko wejścia do sklepu.",
  "addr": "Na ścianie, naprzeciwko wejścia do sklepu.",
  "lat": 50.13649,
  "lon": 18.96905,
  "indoor": true,
  "access": "godziny",
  "hours": "b.d.",
  "signage": false,
  "inspection": "brak",
  "owner": "wg OSM",
  "source": "OSM",
  "osm_id": 11218013238,
  "loc_desc": "Na ścianie, naprzeciwko wejścia do sklepu.",
  "check_date": "",
  "phone": "999"
 },
 {
  "id": "AED-30",
  "name": "Skoła podstawowa nr 6",
  "addr": "Katowicka 102",
  "lat": 50.14593,
  "lon": 18.99944,
  "indoor": true,
  "access": "godziny",
  "hours": "Mo-Fr 07:00-17:00; PH closed",
  "signage": false,
  "inspection": "brak",
  "owner": "Skoła podstawowa nr 6",
  "source": "OSM",
  "osm_id": 11645349982,
  "loc_desc": "Po prawej stronie na ścianie",
  "check_date": "",
  "phone": "+48 322 198 812"
 },
 {
  "id": "AED-31",
  "name": "Mateco podesty ruchome, parter po prawej stronie",
  "addr": "Mateco podesty ruchome, parter po prawej stronie od wejścia. Godziny otwarcia: pon.-pt. 8.00-16.00",
  "lat": 50.14917,
  "lon": 18.95568,
  "indoor": true,
  "access": "godziny",
  "hours": "b.d.",
  "signage": false,
  "inspection": "brak",
  "owner": "wg OSM",
  "source": "OSM",
  "osm_id": 13476588601,
  "loc_desc": "Mateco podesty ruchome, parter po prawej stronie od wejścia. Godziny otwarcia: pon.-pt. 8.00-16.00",
  "check_date": "2026-02-13",
  "phone": ""
 }
]